dsrp_ml_utils/__init__.py
dsrp_ml_utils/ml_utils.py
dsrp_ml_utils/storage.py
dsrp_ml_utils-0.1.0.dist-info/METADATA
dsrp_ml_utils-0.1.0.dist-info/WHEEL
dsrp_ml_utils-0.1.0.dist-info/RECORD
