Metadata-Version: 2.4
Name: dsrp-ml-utils
Version: 0.1.0
Summary: ML utilities for DSRP Machine Learning Engineering course - movie recommendation pipeline
Project-URL: Homepage, https://github.com/dsrp-org/dsrp-machine-learning-engineering-4
Project-URL: Repository, https://github.com/dsrp-org/dsrp-machine-learning-engineering-4
Project-URL: Documentation, https://github.com/dsrp-org/dsrp-machine-learning-engineering-4#readme
Author-email: DSRP <info@dsrp.dev>
License-Expression: MIT
Keywords: dsrp,machine-learning,mlops,recommendation-system
Classifier: Development Status :: 4 - Beta
Classifier: Intended Audience :: Developers
Classifier: Intended Audience :: Science/Research
Classifier: License :: OSI Approved :: MIT License
Classifier: Programming Language :: Python :: 3
Classifier: Programming Language :: Python :: 3.11
Classifier: Programming Language :: Python :: 3.12
Classifier: Topic :: Scientific/Engineering :: Artificial Intelligence
Requires-Python: >=3.11
Requires-Dist: mlflow>=2.0.0
Requires-Dist: numpy>=1.24.0
Requires-Dist: polars>=0.20.0
Requires-Dist: sentence-transformers>=2.2.0
Provides-Extra: all
Requires-Dist: azure-identity>=1.0.0; extra == 'all'
Requires-Dist: azure-storage-blob>=12.0.0; extra == 'all'
Requires-Dist: pytest-cov>=4.0.0; extra == 'all'
Requires-Dist: pytest>=7.0.0; extra == 'all'
Requires-Dist: ruff>=0.1.0; extra == 'all'
Provides-Extra: azure
Requires-Dist: azure-identity>=1.0.0; extra == 'azure'
Requires-Dist: azure-storage-blob>=12.0.0; extra == 'azure'
Provides-Extra: dev
Requires-Dist: pytest-cov>=4.0.0; extra == 'dev'
Requires-Dist: pytest>=7.0.0; extra == 'dev'
Requires-Dist: ruff>=0.1.0; extra == 'dev'
